baal/__init__.py
baal/active/__init__.py
baal/active/active_loop.py
baal/active/dataset/__init__.py
baal/active/dataset/base.py
baal/active/dataset/nlp_datasets.py
baal/active/dataset/numpy.py
baal/active/dataset/pytorch_dataset.py
baal/active/file_dataset.py
baal/active/heuristics/__init__.py
baal/active/heuristics/aliases.py
baal/active/heuristics/heuristics.py
baal/active/heuristics/heuristics_gpu.py
baal/active/heuristics/stochastics.py
baal/active/stopping_criteria.py
baal/bayesian/__init__.py
baal/bayesian/caching_utils.py
baal/bayesian/common.py
baal/bayesian/consistent_dropout.py
baal/bayesian/dropout.py
baal/bayesian/weight_drop.py
baal/calibration/__init__.py
baal/calibration/calibration.py
baal/ensemble.py
baal/experiments/__init__.py
baal/experiments/base.py
baal/experiments/modelwrapper.py
baal/experiments/transformers.py
baal/metrics/__init__.py
baal/metrics/mixin.py
baal/modelwrapper.py
baal/transformers_trainer_wrapper.py
baal/utils/__init__.py
baal/utils/array_utils.py
baal/utils/cuda_utils.py
baal/utils/equality.py
baal/utils/iterutils.py
baal/utils/log_configuration.py
baal/utils/metrics.py
baal/utils/plot_utils.py
baal/utils/pytorch_lightning.py
baal/utils/ssl_iterator.py
baal/utils/ssl_module.py
baal/utils/transforms.py
baal/utils/warnings.py
baal-2.1.0.dist-info/LICENSE
baal-2.1.0.dist-info/METADATA
baal-2.1.0.dist-info/WHEEL
baal-2.1.0.dist-info/RECORD
