Metadata-Version: 2.3
Name: baal
Version: 2.1.0
Summary: Library to enable Bayesian active learning in your research or labeling work.
License: Apache-2.0
Author: Parmida Atighehchian
Author-email: parmida.atighehchian@servicenow.com
Requires-Python: >=3.10,<4
Classifier: License :: OSI Approved :: Apache Software License
Classifier: Programming Language :: Python :: 3
Classifier: Programming Language :: Python :: 3.10
Classifier: Programming Language :: Python :: 3.11
Classifier: Programming Language :: Python :: 3.12
Classifier: Programming Language :: Python :: 3.13
Provides-Extra: nlp
Provides-Extra: vision
Requires-Dist: Pillow (>=6.2.0)
Requires-Dist: accelerate (>=1.8.0,<2.0.0) ; extra == "nlp"
Requires-Dist: datasets (>=2.14.6) ; extra == "nlp"
Requires-Dist: jupyter (>=1.0.0,<2.0.0)
Requires-Dist: lightning-flash (>=0.7.5) ; extra == "vision"
Requires-Dist: matplotlib (>=3.4.3,<4.0.0)
Requires-Dist: numpy (>=2.0.0)
Requires-Dist: scikit-learn (>=1.0.0,<2.0.0)
Requires-Dist: scipy (>=1.7.1,<2.0.0)
Requires-Dist: structlog (>=22.0.0,<23.0.0)
Requires-Dist: torch (>=1.6.0)
Requires-Dist: torchmetrics (>=1.7.3,<2.0.0)
Requires-Dist: torchvision (>=0.7.0) ; extra == "vision"
Requires-Dist: tqdm (>=4.62.2,<5.0.0)
Requires-Dist: transformers (>=4.10.2) ; extra == "nlp"
Project-URL: Documentation, https://baal.readthedocs.io
Project-URL: Repository, https://github.com/ElementAI/baal/
